{"divisions":{"ocd-division/country:us/state:oh/county:putnam":{"name":"Putnam County","officeIndices":[0,1,2,3,4,5,6,7,8]}},"offices":[{"name":"Auditor","divisionId":"ocd-division/country:us/state:oh/county:putnam","officialIndices":[0]},{"name":"Coroner","divisionId":"ocd-division/country:us/state:oh/county:putnam","officialIndices":[1]},{"name":"Sheriff","divisionId":"ocd-division/country:us/state:oh/county:putnam","officialIndices":[2]},{"name":"Recorder","divisionId":"ocd-division/country:us/state:oh/county:putnam","officialIndices":[3]},{"name":"Treasurer","divisionId":"ocd-division/country:us/state:oh/county:putnam","officialIndices":[4]},{"name":"Clerk of Courts","divisionId":"ocd-division/country:us/state:oh/county:putnam","officialIndices":[5]},{"name":"County Engineer","divisionId":"ocd-division/country:us/state:oh/county:putnam","officialIndices":[6]},{"name":"County Commission","divisionId":"ocd-division/country:us/state:oh/county:putnam","officialIndices":[7,8,9]},{"name":"Prosecuting Attorney","divisionId":"ocd-division/country:us/state:oh/county:putnam","officialIndices":[10]}],"officials":[{"name":"Robert Benroth","party":"Republican"},{"name":"Anna Horstman","party":"Republican"},{"name":"Mike Chandler","party":"Republican"},{"name":"Cathy Recker","party":"Republican"},{"name":"Tracy Warnecke","party":"Republican"},{"name":"Teresa Lammers","party":"Democratic"},{"name":"Terrence Recker","party":"Democratic"},{"name":"John E. Love","party":"Democratic"},{"name":"Vincent Schroeder","party":"Republican"},{"name":"John Love","party":"Democratic"},{"name":"Gary Lammers","party":"Democratic"}]}